coco_types/__init__.py
coco_types/coco_keypoints.py
coco_types/coco_object_detection.py
coco_types/py.typed
coco_types/dicts/__init__.py
coco_types/dicts/coco_keypoints.py
coco_types/dicts/coco_object_detection.py
coco_types-0.0.10.dist-info/METADATA
coco_types-0.0.10.dist-info/WHEEL
coco_types-0.0.10.dist-info/licenses/LICENSE.md
coco_types-0.0.10.dist-info/RECORD
