Metadata-Version: 2.1
Name: coco-types
Version: 0.0.10
Summary: Package for handling COCO datasets types.
Project-URL: Homepage, https://github.com/hoel-bagard/coco-types
Project-URL: Bug Tracker, https://github.com/hoel-bagard/coco-types/issues
Author: Bagard Hoel
License: MIT
License-File: LICENSE.md
Keywords: COCO,COCO dataset
Classifier: Intended Audience :: Developers
Classifier: License :: OSI Approved :: MIT License
Classifier: Operating System :: OS Independent
Classifier: Programming Language :: Python :: 3
Classifier: Programming Language :: Python :: 3.10
Classifier: Programming Language :: Python :: 3.11
Requires-Python: >=3.10
Requires-Dist: numpy
Requires-Dist: pydantic
Provides-Extra: build
Requires-Dist: hatch; extra == 'build'
Provides-Extra: dev
Requires-Dist: pip-tools; extra == 'dev'
Requires-Dist: pre-commit; extra == 'dev'
Requires-Dist: pyright; extra == 'dev'
Requires-Dist: ruff; extra == 'dev'
Provides-Extra: flake8
Requires-Dist: flake8; extra == 'flake8'
Requires-Dist: flake8-broken-line; extra == 'flake8'
Requires-Dist: flake8-bugbear; extra == 'flake8'
Requires-Dist: flake8-builtins; extra == 'flake8'
Requires-Dist: flake8-commas; extra == 'flake8'
Requires-Dist: flake8-comprehensions; extra == 'flake8'
Requires-Dist: flake8-docstrings; extra == 'flake8'
Requires-Dist: flake8-import-order; extra == 'flake8'
Requires-Dist: flake8-noqa; extra == 'flake8'
Requires-Dist: flake8-pyproject; extra == 'flake8'
Requires-Dist: flake8-quotes; extra == 'flake8'
Requires-Dist: pep8-naming; extra == 'flake8'
Provides-Extra: test
Requires-Dist: nox; extra == 'test'
Requires-Dist: pytest; extra == 'test'
